powerbiapi/__init__.py
powerbiapi/pbi.py
powerbi_api-0.0.2.dist-info/LICENSE
powerbi_api-0.0.2.dist-info/METADATA
powerbi_api-0.0.2.dist-info/WHEEL
powerbi_api-0.0.2.dist-info/top_level.txt
powerbi_api-0.0.2.dist-info/RECORD
